cert_validate/__init__.py
cert_validate/cert_validate.py
cert_validate-0.0.1.dist-info/LICENSE
cert_validate-0.0.1.dist-info/METADATA
cert_validate-0.0.1.dist-info/WHEEL
cert_validate-0.0.1.dist-info/top_level.txt
cert_validate-0.0.1.dist-info/RECORD
