Metadata-Version: 2.1
Name: cert-validate
Version: 0.0.1
Summary: A small function that gets the expiration date of a certificate of a domain
Home-page: https://github.com/greatbody/cert-validate
Author: greatbody
Author-email: sunruicode@gmail.com
License: UNKNOWN
Project-URL: Bug Tracker, https://github.com/greatbody/cert-validate/issues
Platform: UNKNOWN
Classifier: Programming Language :: Python :: 3
Classifier: License :: OSI Approved :: MIT License
Classifier: Operating System :: OS Independent
Requires-Python: >=3.6
License-File: LICENSE
Requires-Dist: pytz
